github_changelog_md/__init__.py
github_changelog_md/constants.py
github_changelog_md/helpers.py
github_changelog_md/main.py
github_changelog_md/changelog/__init__.py
github_changelog_md/changelog/changelog.py
github_changelog_md/config/__init__.py
github_changelog_md/config/settings.py
github_changelog_md-0.9.6.dist-info/METADATA
github_changelog_md-0.9.6.dist-info/WHEEL
github_changelog_md-0.9.6.dist-info/entry_points.txt
github_changelog_md-0.9.6.dist-info/licenses/LICENSE.txt
github_changelog_md-0.9.6.dist-info/RECORD
