Metadata-Version: 2.4
Name: github-changelog-md
Version: 0.9.6
Summary: Generate a Markdown Changelog from your Github repository.
Project-URL: homepage, https://changelog.seapagan.net
Project-URL: repository, https://github.com/seapagan/github-changelog-md
Project-URL: Pull Requests, https://github.com/seapagan/github-changelog-md/pulls
Project-URL: Bug Tracker, https://github.com/seapagan/github-changelog-md/issues
Project-URL: Changelog, https://github.com/seapagan/github-changelog-md/blob/main/CHANGELOG.md
Author-email: Grant Ramsay <seapagan@gmail.com>
License-Expression: MIT
License-File: LICENSE.txt
Requires-Python: >=3.9
Requires-Dist: pygithub>=2.4.0
Requires-Dist: rich>=13.9.4
Requires-Dist: rtoml>=0.11.0
Requires-Dist: simple-toml-settings>=0.8.0
Requires-Dist: typer>=0.12.5
